panna/__init__.py
panna/model_img2img_controlnet_stable_diffusion_2.py
panna/model_img2img_controlnet_stable_diffusion_3.py
panna/model_img2img_depth2image.py
panna/model_img2img_depth_anything_v2.py
panna/model_img2img_instruct_ir.py
panna/model_img2img_ledits_pp.py
panna/model_img2img_stable_diffusion_upscaler.py
panna/model_img2txt_clip_interrogator.py
panna/model_txt2img_flux_1_dev.py
panna/model_txt2img_image_stable_diffusion_2.py
panna/model_txt2img_image_stable_diffusion_3.py
panna/model_txt2img_image_stable_diffusion_xl.py
panna/model_txt2img_stable_diffusion_3.py
panna/model_txt2img_stable_diffusion_xl.py
panna/util.py
panna/modules_instruct_ir/__init__.py
panna/modules_instruct_ir/instructir.py
panna/modules_instruct_ir/language_models.py
panna/modules_instruct_ir/nafnet.py
panna/modules_instruct_ir/nafnet_utils.py
panna-1.0.3.dist-info/METADATA
panna-1.0.3.dist-info/WHEEL
panna-1.0.3.dist-info/top_level.txt
panna-1.0.3.dist-info/RECORD
