Metadata-Version: 2.4
Name: panna
Version: 1.0.3
Summary: PANNA
Home-page: https://github.com/asahi417
Author: Asahi Ushio
Author-email: asahi1992ushio@gmail.com
License: MIT
Keywords: machine-learning,computational-art
Classifier: Development Status :: 4 - Beta
Classifier: Intended Audience :: Developers
Classifier: Intended Audience :: Science/Research
Classifier: Topic :: Scientific/Engineering
Classifier: License :: OSI Approved :: MIT License
Classifier: Programming Language :: Python :: 3
Requires-Python: >=3.8,<=3.12
Requires-Dist: numpy<2.0.0
Requires-Dist: torch==2.5.0
Requires-Dist: datasets
Requires-Dist: transformers<4.49.0
Requires-Dist: diffusers>=0.19.0
Requires-Dist: invisible_watermark
Requires-Dist: accelerate
Requires-Dist: safetensors
Requires-Dist: sentencepiece
Requires-Dist: protobuf
Requires-Dist: accelerate
Requires-Dist: bitsandbytes
Requires-Dist: DeepCache
Requires-Dist: opencv-python
Requires-Dist: timm<=1.0.15
Dynamic: author
Dynamic: author-email
Dynamic: classifier
Dynamic: description
Dynamic: description-content-type
Dynamic: home-page
Dynamic: keywords
Dynamic: license
Dynamic: requires-dist
Dynamic: requires-python
Dynamic: summary
